testmyesp
