Metadata-Version: 1.0
Name: testmyesp
Version: 0.6.2
Summary: A tool to run automated tests for the ESP8266.
Home-page: https://gitlab.com/ccrisan/testmyesp
Author: Calin Crisan
Author-email: UNKNOWN
License: GPL
Platform: UNKNOWN
